[
	{
		"inputs": [
			{
				"internalType": "uint256",
				"name": "_uid",
				"type": "uint256"
			},
			{
				"internalType": "string",
				"name": "_comment_msg",
				"type": "string"
			}
		],
		"name": "addComment",
		"outputs": [],
		"stateMutability": "nonpayable",
		"type": "function"
	},
	{
		"inputs": [
			{
				"internalType": "string",
				"name": "_title",
				"type": "string"
			},
			{
				"internalType": "string",
				"name": "_image_url",
				"type": "string"
			},
			{
				"internalType": "string",
				"name": "_report_msg",
				"type": "string"
			},
			{
				"internalType": "string",
				"name": "_username",
				"type": "string"
			},
			{
				"internalType": "string",
				"name": "_location",
				"type": "string"
			},
			{
				"internalType": "string",
				"name": "_governmentBody",
				"type": "string"
			}
		],
		"name": "addReport",
		"outputs": [],
		"stateMutability": "nonpayable",
		"type": "function"
	},
	{
		"inputs": [
			{
				"internalType": "uint256",
				"name": "_uid",
				"type": "uint256"
			}
		],
		"name": "likeTheReport",
		"outputs": [],
		"stateMutability": "nonpayable",
		"type": "function"
	},
	{
		"inputs": [
			{
				"internalType": "string",
				"name": "_username",
				"type": "string"
			}
		],
		"name": "setUsername",
		"outputs": [],
		"stateMutability": "nonpayable",
		"type": "function"
	},
	{
		"inputs": [],
		"stateMutability": "nonpayable",
		"type": "constructor"
	},
	{
		"anonymous": false,
		"inputs": [
			{
				"indexed": false,
				"internalType": "string",
				"name": "_title",
				"type": "string"
			},
			{
				"indexed": false,
				"internalType": "string",
				"name": "_image_url",
				"type": "string"
			},
			{
				"indexed": false,
				"internalType": "string",
				"name": "_report_msg",
				"type": "string"
			},
			{
				"indexed": false,
				"internalType": "string",
				"name": "_username",
				"type": "string"
			},
			{
				"indexed": false,
				"internalType": "string",
				"name": "_location",
				"type": "string"
			},
			{
				"indexed": false,
				"internalType": "string",
				"name": "_governmentBody",
				"type": "string"
			}
		],
		"name": "addReportEvent",
		"type": "event"
	},
	{
		"inputs": [],
		"name": "count",
		"outputs": [
			{
				"internalType": "uint256",
				"name": "",
				"type": "uint256"
			}
		],
		"stateMutability": "view",
		"type": "function"
	},
	{
		"inputs": [
			{
				"internalType": "uint256",
				"name": "_uid",
				"type": "uint256"
			}
		],
		"name": "getComment",
		"outputs": [
			{
				"components": [
					{
						"internalType": "string",
						"name": "comment_msg",
						"type": "string"
					},
					{
						"internalType": "address",
						"name": "owner_comment",
						"type": "address"
					}
				],
				"internalType": "struct Reporter.Comment[]",
				"name": "",
				"type": "tuple[]"
			}
		],
		"stateMutability": "view",
		"type": "function"
	},
	{
		"inputs": [
			{
				"internalType": "uint256",
				"name": "_uid",
				"type": "uint256"
			}
		],
		"name": "getLikesOfReport",
		"outputs": [
			{
				"internalType": "uint256",
				"name": "",
				"type": "uint256"
			}
		],
		"stateMutability": "view",
		"type": "function"
	},
	{
		"inputs": [],
		"name": "getReports",
		"outputs": [
			{
				"components": [
					{
						"internalType": "uint256",
						"name": "uid",
						"type": "uint256"
					},
					{
						"internalType": "string",
						"name": "title",
						"type": "string"
					},
					{
						"internalType": "string",
						"name": "image_url",
						"type": "string"
					},
					{
						"internalType": "string",
						"name": "report_msg",
						"type": "string"
					},
					{
						"internalType": "uint256",
						"name": "timestamp",
						"type": "uint256"
					},
					{
						"internalType": "address",
						"name": "owner",
						"type": "address"
					},
					{
						"internalType": "string",
						"name": "userName",
						"type": "string"
					},
					{
						"internalType": "string",
						"name": "location",
						"type": "string"
					},
					{
						"internalType": "string",
						"name": "governmentBody",
						"type": "string"
					}
				],
				"internalType": "struct Reporter.Report[]",
				"name": "",
				"type": "tuple[]"
			}
		],
		"stateMutability": "view",
		"type": "function"
	},
	{
		"inputs": [],
		"name": "getUserLikes",
		"outputs": [
			{
				"internalType": "uint256[]",
				"name": "",
				"type": "uint256[]"
			}
		],
		"stateMutability": "view",
		"type": "function"
	},
	{
		"inputs": [
			{
				"internalType": "address",
				"name": "_userAddress",
				"type": "address"
			}
		],
		"name": "getUsername",
		"outputs": [
			{
				"internalType": "string",
				"name": "",
				"type": "string"
			}
		],
		"stateMutability": "view",
		"type": "function"
	},
	{
		"inputs": [],
		"name": "getUserTweets",
		"outputs": [
			{
				"components": [
					{
						"internalType": "uint256",
						"name": "uid",
						"type": "uint256"
					},
					{
						"internalType": "string",
						"name": "title",
						"type": "string"
					},
					{
						"internalType": "string",
						"name": "image_url",
						"type": "string"
					},
					{
						"internalType": "string",
						"name": "report_msg",
						"type": "string"
					},
					{
						"internalType": "uint256",
						"name": "timestamp",
						"type": "uint256"
					},
					{
						"internalType": "address",
						"name": "owner",
						"type": "address"
					},
					{
						"internalType": "string",
						"name": "userName",
						"type": "string"
					},
					{
						"internalType": "string",
						"name": "location",
						"type": "string"
					},
					{
						"internalType": "string",
						"name": "governmentBody",
						"type": "string"
					}
				],
				"internalType": "struct Reporter.Report[]",
				"name": "",
				"type": "tuple[]"
			}
		],
		"stateMutability": "view",
		"type": "function"
	},
	{
		"inputs": [],
		"name": "owner",
		"outputs": [
			{
				"internalType": "address payable",
				"name": "",
				"type": "address"
			}
		],
		"stateMutability": "view",
		"type": "function"
	},
	{
		"inputs": [
			{
				"internalType": "uint256",
				"name": "",
				"type": "uint256"
			}
		],
		"name": "tweets",
		"outputs": [
			{
				"internalType": "uint256",
				"name": "uid",
				"type": "uint256"
			},
			{
				"internalType": "string",
				"name": "title",
				"type": "string"
			},
			{
				"internalType": "string",
				"name": "image_url",
				"type": "string"
			},
			{
				"internalType": "string",
				"name": "report_msg",
				"type": "string"
			},
			{
				"internalType": "uint256",
				"name": "timestamp",
				"type": "uint256"
			},
			{
				"internalType": "address",
				"name": "owner",
				"type": "address"
			},
			{
				"internalType": "string",
				"name": "userName",
				"type": "string"
			},
			{
				"internalType": "string",
				"name": "location",
				"type": "string"
			},
			{
				"internalType": "string",
				"name": "governmentBody",
				"type": "string"
			}
		],
		"stateMutability": "view",
		"type": "function"
	},
	{
		"inputs": [
			{
				"internalType": "address",
				"name": "",
				"type": "address"
			}
		],
		"name": "usernames",
		"outputs": [
			{
				"internalType": "string",
				"name": "",
				"type": "string"
			}
		],
		"stateMutability": "view",
		"type": "function"
	}
]